odoo/addons/sm_rest_api/__init__.py
odoo/addons/sm_rest_api/__manifest__.py
odoo/addons/sm_rest_api/models/__init__.py
odoo/addons/sm_rest_api/models/models.py
odoo12_addon_sm_rest_api-12.0.0.0.1.dist-info/METADATA
odoo12_addon_sm_rest_api-12.0.0.0.1.dist-info/WHEEL
odoo12_addon_sm_rest_api-12.0.0.0.1.dist-info/top_level.txt
odoo12_addon_sm_rest_api-12.0.0.0.1.dist-info/RECORD
