Metadata-Version: 2.1
Name: odoo12-addon-sm-rest-api
Version: 12.0.0.0.1
Summary: REST API implementation for carsharing system
Home-page: http://www.yourcompany.com
Author: Som Mobilitat
License: UNKNOWN
Platform: UNKNOWN
Classifier: Programming Language :: Python
Classifier: Framework :: Odoo
Requires-Python: >=3.5
Requires-Dist: odoo (<12.1dev,>=12.0a)
